dhcs_algorithm/__init__.py
dhcs_algorithm/dhcs.py
dhcs_algorithm-1.0.0.dist-info/METADATA
dhcs_algorithm-1.0.0.dist-info/WHEEL
dhcs_algorithm-1.0.0.dist-info/license
dhcs_algorithm-1.0.0.dist-info/top_level.txt
dhcs_algorithm-1.0.0.dist-info/RECORD
