Metadata-Version: 2.2
Name: dhcs_algorithm
Version: 1.0.0
Summary: Dynamic Hierarchical Cooperative Swarm Optimization (DHCS)
Home-page: https://github.com/bajpaikrishna/DHCS
Author: Your Name
Author-email: bajpaikrishna715@gmail.com
License: MIT
Classifier: Programming Language :: Python :: 3
Classifier: License :: OSI Approved :: MIT License
Classifier: Operating System :: OS Independent
Classifier: Topic :: Scientific/Engineering :: Artificial Intelligence
Requires-Python: >=3.7
License-File: license
Requires-Dist: numpy
